salina/__init__.py
salina-0.0.1.dist-info/METADATA
salina-0.0.1.dist-info/WHEEL
salina-0.0.1.dist-info/top_level.txt
salina-0.0.1.dist-info/RECORD
