Metadata-Version: 2.4
Name: salina
Version: 0.0.1
Summary: Dummy lock package for salina
Author: AutoPublisher
